Workbook

Sheet Weekly Raw Data
A1: SKU ID | B1: Brand | C1: Segment | D1: Pack Size | E1: Channel | F1: GSV Plan ($K) W1 (29-Dec) | G1: GSV Actual ($K) W1 (29-Dec) | H1: GSV LE ($K) W1 (29-Dec) | I1: Trade Plan ($K) W1 (29-Dec) | J1: Trade Actual ($K) W1 (29-Dec) | K1: Trade LE ($K) W1 (29-Dec) | L1: GSV Plan ($K) W2 (05-Jan) | M1: GSV Actual ($K) W2 (05-Jan) | N1: GSV LE ($K) W2 (05-Jan) | O1: Trade Plan ($K) W2 (05-Jan) | P1: Trade Actual ($K) W2 (05-Jan) | Q1: Trade LE ($K) W2 (05-Jan) | R1: GSV Plan ($K) W3 (12-Jan) | S1: GSV Actual ($K) W3 (12-Jan) | T1: GSV LE ($K) W3 (12-Jan) | U1: Trade Plan ($K) W3 (12-Jan) | V1: Trade Actual ($K) W3 (12-Jan) | W1: Trade LE ($K) W3 (12-Jan) | X1: GSV Plan ($K) W4 (19-Jan) | Y1: GSV Actual ($K) W4 (19-Jan) | Z1: GSV LE ($K) W4 (19-Jan) | AA1: Trade Plan ($K) W4 (19-Jan) | AB1: Trade Actual ($K) W4 (19-Jan) | AC1: Trade LE ($K) W4 (19-Jan) | AD1: GSV Plan ($K) W5 (26-Jan) | AE1: GSV Actual ($K) W5 (26-Jan) | AF1: GSV LE ($K) W5 (26-Jan) | AG1: Trade Plan ($K) W5 (26-Jan) | AH1: Trade Actual ($K) W5 (26-Jan) | AI1: Trade LE ($K) W5 (26-Jan) | AJ1: GSV Plan ($K) W6 (02-Feb) | AK1: GSV Actual ($K) W6 (02-Feb) | AL1: GSV LE ($K) W6 (02-Feb) | AM1: Trade Plan ($K) W6 (02-Feb) | AN1: Trade Actual ($K) W6 (02-Feb) | AO1: Trade LE ($K) W6 (02-Feb) | AP1: GSV Plan ($K) W7 (09-Feb) | AQ1: GSV Actual ($K) W7 (09-Feb) | AR1: GSV LE ($K) W7 (09-Feb) | AS1: Trade Plan ($K) W7 (09-Feb) | AT1: Trade Actual ($K) W7 (09-Feb) | AU1: Trade LE ($K) W7 (09-Feb) | AV1: GSV Plan ($K) W8 (16-Feb) | AW1: GSV Actual ($K) W8 (16-Feb) | AX1: GSV LE ($K) W8 (16-Feb) | AY1: Trade Plan ($K) W8 (16-Feb) | AZ1: Trade Actual ($K) W8 (16-Feb) | BA1: Trade LE ($K) W8 (16-Feb) | BB1: GSV Plan ($K) W9 (23-Feb) | BC1: GSV Actual ($K) W9 (23-Feb) | BD1: GSV LE ($K) W9 (23-Feb) | BE1: Trade Plan ($K) W9 (23-Feb) | BF1: Trade Actual ($K) W9 (23-Feb) | BG1: Trade LE ($K) W9 (23-Feb) | BH1: GSV Plan ($K) W10 (02-Mar) | BI1: GSV Actual ($K) W10 (02-Mar) | BJ1: GSV LE ($K) W10 (02-Mar) | BK1: Trade Plan ($K) W10 (02-Mar) | BL1: Trade Actual ($K) W10 (02-Mar) | BM1: Trade LE ($K) W10 (02-Mar) | BN1: GSV Plan ($K) W11 (09-Mar) | BO1: GSV Actual ($K) W11 (09-Mar) | BP1: GSV LE ($K) W11 (09-Mar) | BQ1: Trade Plan ($K) W11 (09-Mar) | BR1: Trade Actual ($K) W11 (09-Mar) | BS1: Trade LE ($K) W11 (09-Mar) | BT1: GSV Plan ($K) W12 (16-Mar) | BU1: GSV Actual ($K) W12 (16-Mar) | BV1: GSV LE ($K) W12 (16-Mar) | BW1: Trade Plan ($K) W12 (16-Mar) | BX1: Trade Actual ($K) W12 (16-Mar) | BY1: Trade LE ($K) W12 (16-Mar) | BZ1: GSV Plan ($K) W13 (23-Mar) | CA1: GSV Actual ($K) W13 (23-Mar) | CB1: GSV LE ($K) W13 (23-Mar) | CC1: Trade Plan ($K) W13 (23-Mar) | CD1: Trade Actual ($K) W13 (23-Mar) | CE1: Trade LE ($K) W13 (23-Mar)
A2: PF-001 | B2: NutriPaws | C2: Dry Dog Food | D2: 5kg | E2: Grocery | F2: 80.8 | G2: 82.6 | H2: 80.3 | I2: 14.5 | J2: 14.3 | K2: 14.1 | L2: 80.8 | M2: 113.2 | N2: 115.2 | O2: 14.5 | P2: 22.3 | Q2: 19.9 | R2: 80.8 | S2: 79.8 | T2: 77.6 | U2: 14.5 | V2: 13.6 | W2: 14 | X2: 80.8 | Y2: 74.7 | Z2: 73.5 | AA2: 14.5 | AB2: 14 | AC2: 13.3 | AD2: 80.8 | AE2: 77.2 | AF2: 78.1 | AG2: 14.5 | AH2: 15 | AI2: 13.4 | AJ2: 80.8 | AK2: 114.4 | AL2: 116.6 | AM2: 14.5 | AN2: 20.1 | AO2: 20.3 | AP2: 80.8 | AQ2: 86.7 | AR2: 86.1 | AS2: 14.5 | AT2: 14.4 | AU2: 14.9 | AV2: 80.8 | AW2: 85.3 | AX2: 86.3 | AY2: 14.5 | AZ2: 16.5 | BA2: 15.9 | BB2: 80.8 | BC2: 81.2 | BD2: 84.3 | BE2: 14.5 | BF2: 14.4 | BG2: 15.3 | BH2: 80.8 | BI2: 114.8 | BJ2: 116.3 | BK2: 14.5 | BL2: 22.5 | BM2: 21.1 | BN2: 80.8 | BO2: 83.4 | BP2: 81.2 | BQ2: 14.5 | BR2: 14.3 | BS2: 14.3 | BT2: 80.8 | BU2: 75.3 | BV2: 74.3 | BW2: 14.5 | BX2: 12.5 | BY2: 13.1 | BZ2: 80.8 | CA2: 82.5 | CB2: 82.1 | CC2: 14.5 | CD2: 14.6 | CE2: 14.3
A3: PF-002 | B3: NutriPaws | C3: Dry Dog Food | D3: 12kg | E3: Grocery | F3: 150 | G3: 144.4 | H3: 149.5 | I3: 30 | J3: 30.1 | K3: 30.2 | L3: 150 | M3: 142.1 | N3: 145.1 | O3: 30 | P3: 26.6 | Q3: 28.7 | R3: 150 | S3: 218.4 | T3: 221.6 | U3: 30 | V3: 44.7 | W3: 45.1 | X3: 150 | Y3: 158.2 | Z3: 162 | AA3: 30 | AB3: 30.1 | AC3: 30.9 | AD3: 150 | AE3: 145.6 | AF3: 144 | AG3: 30 | AH3: 27.6 | AI3: 30.1 | AJ3: 150 | AK3: 159 | AL3: 157.7 | AM3: 30 | AN3: 33.2 | AO3: 31.2 | AP3: 150 | AQ3: 215.9 | AR3: 216.4 | AS3: 30 | AT3: 41.4 | AU3: 42.2 | AV3: 150 | AW3: 151.5 | AX3: 149.7 | AY3: 30 | AZ3: 31.2 | BA3: 31.1 | BB3: 150 | BC3: 147.6 | BD3: 145.4 | BE3: 30 | BF3: 33 | BG3: 29.1 | BH3: 150 | BI3: 140.2 | BJ3: 136.5 | BK3: 30 | BL3: 25.9 | BM3: 27.6 | BN3: 150 | BO3: 212 | BP3: 211.9 | BQ3: 30 | BR3: 38.8 | BS3: 41.9 | BT3: 150 | BU3: 161.9 | BV3: 163 | BW3: 30 | BX3: 36.1 | BY3: 33.8 | BZ3: 150 | CA3: 138.3 | CB3: 141.1 | CC3: 30 | CD3: 29 | CE3: 28.3
A4: PF-003 | B4: NutriPaws | C4: Wet Dog Food | D4: 400g x6 | E4: Grocery | F4: 59.6 | G4: 77.5 | H4: 78.7 | I4: 13.1 | J4: 15.8 | K4: 17.2 | L4: 59.6 | M4: 59.2 | N4: 61.4 | O4: 13.1 | P4: 14.2 | Q4: 13.2 | R4: 59.6 | S4: 59.6 | T4: 58.6 | U4: 13.1 | V4: 14.4 | W4: 13.4 | X4: 59.6 | Y4: 57.7 | Z4: 58.5 | AA4: 13.1 | AB4: 13.1 | AC4: 12.4 | AD4: 59.6 | AE4: 83.9 | AF4: 84.6 | AG4: 13.1 | AH4: 19.8 | AI4: 18.7 | AJ4: 59.6 | AK4: 54.9 | AL4: 54.5 | AM4: 13.1 | AN4: 10.9 | AO4: 12.5 | AP4: 59.6 | AQ4: 63.2 | AR4: 65 | AS4: 13.1 | AT4: 13.5 | AU4: 13.7 | AV4: 59.6 | AW4: 63.2 | AX4: 65.5 | AY4: 13.1 | AZ4: 12.8 | BA4: 14.4 | BB4: 59.6 | BC4: 74.9 | BD4: 76.6 | BE4: 13.1 | BF4: 17.6 | BG4: 16.2 | BH4: 59.6 | BI4: 59.4 | BJ4: 59.9 | BK4: 13.1 | BL4: 12.5 | BM4: 13.7 | BN4: 59.6 | BO4: 58.9 | BP4: 58 | BQ4: 13.1 | BR4: 13.2 | BS4: 13.1 | BT4: 59.6 | BU4: 56.8 | BV4: 56.3 | BW4: 13.1 | BX4: 14 | BY4: 12.6 | BZ4: 59.6 | CA4: 79.7 | CB4: 80.2 | CC4: 13.1 | CD4: 16.2 | CE4: 17.2
A5: PF-004 | B5: VitaCat | C5: Dry Cat Food | D5: 2kg | E5: Grocery | F5: 50 | G5: 48.7 | H5: 49.2 | I5: 8.5 | J5: 7.9 | K5: 8.1 | L5: 50 | M5: 46.6 | N5: 47.3 | O5: 8.5 | P5: 7.5 | Q5: 8.4 | R5: 50 | S5: 52.9 | T5: 51.6 | U5: 8.5 | V5: 8.6 | W5: 8.9 | X5: 50 | Y5: 64.4 | Z5: 63.1 | AA5: 8.5 | AB5: 12.1 | AC5: 10.8 | AD5: 50 | AE5: 49.8 | AF5: 51 | AG5: 8.5 | AH5: 9.1 | AI5: 8.4 | AJ5: 50 | AK5: 46.8 | AL5: 46.8 | AM5: 8.5 | AN5: 7.9 | AO5: 7.9 | AP5: 50 | AQ5: 51.8 | AR5: 52.7 | AS5: 8.5 | AT5: 9.8 | AU5: 8.6 | AV5: 50 | AW5: 66.4 | AX5: 66 | AY5: 8.5 | AZ5: 12.3 | BA5: 10.9 | BB5: 50 | BC5: 47.5 | BD5: 47.6 | BE5: 8.5 | BF5: 8 | BG5: 7.9 | BH5: 50 | BI5: 48 | BJ5: 49.7 | BK5: 8.5 | BL5: 8.1 | BM5: 8.8 | BN5: 50 | BO5: 50.4 | BP5: 49.1 | BQ5: 8.5 | BR5: 9.6 | BS5: 8.6 | BT5: 50 | BU5: 53.8 | BV5: 55.7 | BW5: 8.5 | BX5: 9.9 | BY5: 9.2 | BZ5: 50 | CA5: 49.9 | CB5: 49.1 | CC5: 8.5 | CD5: 8.4 | CE5: 8
A6: PF-005 | B6: VitaCat | C6: Wet Cat Food | D6: 85g x12 | E6: Grocery | F6: 36.5 | G6: 35.8 | H6: 37.2 | I6: 9.1 | J6: 8.6 | K6: 9.6 | L6: 36.5 | M6: 49 | N6: 49 | O6: 9.1 | P6: 13.6 | Q6: 12.9 | R6: 36.5 | S6: 36.9 | T6: 37.6 | U6: 9.1 | V6: 8.6 | W6: 9.2 | X6: 36.5 | Y6: 39.3 | Z6: 39.7 | AA6: 9.1 | AB6: 10 | AC6: 10.2 | AD6: 36.5 | AE6: 33.9 | AF6: 34.3 | AG6: 9.1 | AH6: 8.6 | AI6: 8.9 | AJ6: 36.5 | AK6: 46.6 | AL6: 48.3 | AM6: 9.1 | AN6: 10.7 | AO6: 11.7 | AP6: 36.5 | AQ6: 37.1 | AR6: 37.7 | AS6: 9.1 | AT6: 8.8 | AU6: 9.1 | AV6: 36.5 | AW6: 38.8 | AX6: 38.3 | AY6: 9.1 | AZ6: 10 | BA6: 9.7 | BB6: 36.5 | BC6: 36.1 | BD6: 36.5 | BE6: 9.1 | BF6: 9.2 | BG6: 9.5 | BH6: 36.5 | BI6: 47 | BJ6: 47.9 | BK6: 9.1 | BL6: 11.2 | BM6: 11.9 | BN6: 36.5 | BO6: 37.5 | BP6: 37.2 | BQ6: 9.1 | BR6: 9.1 | BS6: 9.5 | BT6: 36.5 | BU6: 34 | BV6: 34.1 | BW6: 9.1 | BX6: 9.5 | BY6: 8.9 | BZ6: 36.5 | CA6: 34 | CB6: 33.5 | CC6: 9.1 | CD6: 8.1 | CE6: 8.7
A7: PF-006 | B7: VitaCat | C7: Dry Cat Food | D7: 5kg | E7: Mass | F7: 65.4 | G7: 69.4 | H7: 71.6 | I7: 12.4 | J7: 12.9 | K7: 13.1 | L7: 65.4 | M7: 68.9 | N7: 70.2 | O7: 12.4 | P7: 13.5 | Q7: 14 | R7: 65.4 | S7: 90.4 | T7: 87.7 | U7: 12.4 | V7: 18.5 | W7: 16.3 | X7: 65.4 | Y7: 67.1 | Z7: 69.5 | AA7: 12.4 | AB7: 11.9 | AC7: 12.7 | AD7: 65.4 | AE7: 61.3 | AF7: 61.8 | AG7: 12.4 | AH7: 11.2 | AI7: 11.9 | AJ7: 65.4 | AK7: 67.7 | AL7: 66.6 | AM7: 12.4 | AN7: 13.4 | AO7: 12.4 | AP7: 65.4 | AQ7: 65.3 | AR7: 67.5 | AS7: 12.4 | AT7: 13.5 | AU7: 12.3 | AV7: 65.4 | AW7: 64.6 | AX7: 63.9 | AY7: 12.4 | AZ7: 11.1 | BA7: 12.5 | BB7: 65.4 | BC7: 66.8 | BD7: 66 | BE7: 12.4 | BF7: 13.5 | BG7: 12.6 | BH7: 65.4 | BI7: 64.6 | BJ7: 62.7 | BK7: 12.4 | BL7: 11.2 | BM7: 12.4 | BN7: 65.4 | BO7: 94 | BP7: 94.8 | BQ7: 12.4 | BR7: 19.4 | BS7: 18.2 | BT7: 65.4 | BU7: 61.7 | BV7: 60.4 | BW7: 12.4 | BX7: 11.3 | BY7: 11.9 | BZ7: 65.4 | CA7: 68.5 | CB7: 70.6 | CC7: 12.4 | CD7: 14.3 | CE7: 13
A8: PF-007 | B8: PureProtein | C8: Dry Dog Food | D8: 8kg | E8: Mass | F8: 98.1 | G8: 127.1 | H8: 124.2 | I8: 20.6 | J8: 28.6 | K8: 27.1 | L8: 98.1 | M8: 96.6 | N8: 97.9 | O8: 20.6 | P8: 18.9 | Q8: 21.4 | R8: 98.1 | S8: 103.8 | T8: 107.8 | U8: 20.6 | V8: 23.5 | W8: 23.5 | X8: 98.1 | Y8: 90.6 | Z8: 92.6 | AA8: 20.6 | AB8: 18.5 | AC8: 20.3 | AD8: 98.1 | AE8: 102.8 | AF8: 105.9 | AG8: 20.6 | AH8: 23.3 | AI8: 21.7 | AJ8: 98.1 | AK8: 102.6 | AL8: 100.3 | AM8: 20.6 | AN8: 23.5 | AO8: 21.8 | AP8: 98.1 | AQ8: 126.5 | AR8: 129.9 | AS8: 20.6 | AT8: 26.6 | AU8: 26.7 | AV8: 98.1 | AW8: 102.7 | AX8: 101.3 | AY8: 20.6 | AZ8: 19.5 | BA8: 20.6 | BB8: 98.1 | BC8: 95.4 | BD8: 98.3 | BE8: 20.6 | BF8: 22.3 | BG8: 20.2 | BH8: 98.1 | BI8: 100.3 | BJ8: 100.1 | BK8: 20.6 | BL8: 23.5 | BM8: 21.1 | BN8: 98.1 | BO8: 105 | BP8: 102.7 | BQ8: 20.6 | BR8: 24.6 | BS8: 20.9 | BT8: 98.1 | BU8: 105.3 | BV8: 104.1 | BW8: 20.6 | BX8: 20.4 | BY8: 21.7 | BZ8: 98.1 | CA8: 137.2 | CB8: 136.1 | CC8: 20.6 | CD8: 29.8 | CE8: 28.6
A9: PF-008 | B9: PureProtein | C9: Treats & Snacks | D9: 200g | E9: Grocery | F9: 23.1 | G9: 22.7 | H9: 22.9 | I9: 3.5 | J9: 3.3 | K9: 3.5 | L9: 23.1 | M9: 21.2 | N9: 21.9 | O9: 3.5 | P9: 3.2 | Q9: 3.4 | R9: 23.1 | S9: 24 | T9: 24.4 | U9: 3.5 | V9: 3.5 | W9: 3.5 | X9: 23.1 | Y9: 23.7 | Z9: 23.5 | AA9: 3.5 | AB9: 3.4 | AC9: 3.6 | AD9: 23.1 | AE9: 32.2 | AF9: 31.9 | AG9: 3.5 | AH9: 4.7 | AI9: 4.7 | AJ9: 23.1 | AK9: 22.7 | AL9: 22.5 | AM9: 3.5 | AN9: 3.2 | AO9: 3.3 | AP9: 23.1 | AQ9: 24.7 | AR9: 25.1 | AS9: 3.5 | AT9: 4.1 | AU9: 3.8 | AV9: 23.1 | AW9: 22.3 | AX9: 22.5 | AY9: 3.5 | AZ9: 3 | BA9: 3.3 | BB9: 23.1 | BC9: 30.8 | BD9: 31.1 | BE9: 3.5 | BF9: 4.8 | BG9: 4.6 | BH9: 23.1 | BI9: 22.9 | BJ9: 22.6 | BK9: 3.5 | BL9: 3.4 | BM9: 3.5 | BN9: 23.1 | BO9: 24.2 | BP9: 23.8 | BQ9: 3.5 | BR9: 3.3 | BS9: 3.6 | BT9: 23.1 | BU9: 23.6 | BV9: 23.4 | BW9: 3.5 | BX9: 3.8 | BY9: 3.6 | BZ9: 23.1 | CA9: 23.7 | CB9: 23.4 | CC9: 3.5 | CD9: 3.4 | CE9: 3.3
A10: PF-009 | B10: PureProtein | C10: Treats & Snacks | D10: 500g | E10: Mass | F10: 34.6 | G10: 33.2 | H10: 33.3 | I10: 5.5 | J10: 5.8 | K10: 5.1 | L10: 34.6 | M10: 34.1 | N10: 34.6 | O10: 5.5 | P10: 5.1 | Q10: 5.6 | R10: 34.6 | S10: 34.6 | T10: 34.2 | U10: 5.5 | V10: 5.8 | W10: 5.2 | X10: 34.6 | Y10: 48.6 | Z10: 49.8 | AA10: 5.5 | AB10: 7.2 | AC10: 7.9 | AD10: 34.6 | AE10: 32.8 | AF10: 34 | AG10: 5.5 | AH10: 5.3 | AI10: 5.2 | AJ10: 34.6 | AK10: 33.2 | AL10: 34.2 | AM10: 5.5 | AN10: 5.3 | AO10: 5.6 | AP10: 34.6 | AQ10: 35.5 | AR10: 36.9 | AS10: 5.5 | AT10: 5.9 | AU10: 6.2 | AV10: 34.6 | AW10: 49.7 | AX10: 50.3 | AY10: 5.5 | AZ10: 8.4 | BA10: 8.1 | BB10: 34.6 | BC10: 36.4 | BD10: 36.7 | BE10: 5.5 | BF10: 6.4 | BG10: 6 | BH10: 34.6 | BI10: 34.5 | BJ10: 34.1 | BK10: 5.5 | BL10: 5.3 | BM10: 5.5 | BN10: 34.6 | BO10: 36.1 | BP10: 36.3 | BQ10: 5.5 | BR10: 6 | BS10: 5.7 | BT10: 34.6 | BU10: 43.6 | BV10: 43.2 | BW10: 5.5 | BX10: 6.7 | BY10: 6.8 | BZ10: 34.6 | CA10: 34.8 | CB10: 34.1 | CC10: 5.5 | CD10: 5.3 | CE10: 5.6
A11: PF-010 | B11: NutriPaws | C11: Dry Dog Food | D11: 20kg | E11: Pet Specialty | F11: 125 | G11: 129.1 | H11: 125.8 | I11: 28.8 | J11: 29.4 | K11: 29.1 | L11: 125 | M11: 166.5 | N11: 163.9 | O11: 28.8 | P11: 38 | Q11: 39.2 | R11: 125 | S11: 126.7 | T11: 129.1 | U11: 28.8 | V11: 31.7 | W11: 30.5 | X11: 125 | Y11: 122.6 | Z11: 119 | AA11: 28.8 | AB11: 27.6 | AC11: 28.1 | AD11: 125 | AE11: 132.1 | AF11: 137 | AG11: 28.8 | AH11: 30.1 | AI11: 32.3 | AJ11: 125 | AK11: 170 | AL11: 172.1 | AM11: 28.8 | AN11: 37.1 | AO11: 38.5 | AP11: 125 | AQ11: 123.7 | AR11: 120.2 | AS11: 28.8 | AT11: 27.7 | AU11: 28.1 | AV11: 125 | AW11: 123.1 | AX11: 120.8 | AY11: 28.8 | AZ11: 28.4 | BA11: 26.7 | BB11: 125 | BC11: 127.4 | BD11: 123.8 | BE11: 28.8 | BF11: 28.9 | BG11: 28.7 | BH11: 125 | BI11: 156 | BJ11: 158.3 | BK11: 28.8 | BL11: 33.4 | BM11: 36.3 | BN11: 125 | BO11: 116 | BP11: 115.6 | BQ11: 28.8 | BR11: 25.3 | BS11: 26.1 | BT11: 125 | BU11: 130.2 | BV11: 129.7 | BW11: 28.8 | BX11: 31.9 | BY11: 30.8 | BZ11: 125 | CA11: 120 | CB11: 117.1 | CC11: 28.8 | CD11: 25 | CE11: 27

Sheet 13W Summary Dashboard
A1: Pet Food RGM – 13-Week GSV & Trade Spend Summary (Latest Estimate vs Plan)
A2: SKU ID | B2: Brand | C2: Segment | D2: Channel | E2: GSV Plan 13W ($K) | F2: GSV Actual 13W ($K) | G2: GSV LE 13W ($K) | H2: GSV Var Actual vs Plan | I2: GSV Var% Actual vs Plan | J2: GSV Var LE vs Plan | K2: GSV Var% LE vs Plan | L2: Trade Plan 13W ($K) | M2: Trade Actual 13W ($K) | N2: Trade LE 13W ($K) | O2: Trade Var Actual vs Plan | P2: Trade Var% Actual vs Plan | Q2: NSV Actual 13W ($K) | R2: NSV Plan 13W ($K) | S2: NSV Var Actual vs Plan
A3: PF-001 | B3: NutriPaws | C3: Dry Dog Food | D3: Grocery | E3: ='Weekly Raw Data'!F2+'Weekly Raw Data'!L2+'Weekly Raw Data'!R2+'Weekly Raw Data'!X2+'Weekly Raw Data'!AD2+'Weekly Raw Data'!AJ2+'Weekly Raw Data'!AP2+'Weekly Raw Data'!AV2+'Weekly Raw Data'!BB2+'Weekly Raw Data'!BH2+'Weekly Raw Data'!BN2+'Weekly Raw Data'!BT2+'Weekly Raw Data'!BZ2 -> 1050.4 | F3: ='Weekly Raw Data'!G2+'Weekly Raw Data'!M2+'Weekly Raw Data'!S2+'Weekly Raw Data'!Y2+'Weekly Raw Data'!AE2+'Weekly Raw Data'!AK2+'Weekly Raw Data'!AQ2+'Weekly Raw Data'!AW2+'Weekly Raw Data'!BC2+'Weekly Raw Data'!BI2+'Weekly Raw Data'!BO2+'Weekly Raw Data'!BU2+'Weekly Raw Data'!CA2 -> 1151.1 | G3: ='Weekly Raw Data'!H2+'Weekly Raw Data'!N2+'Weekly Raw Data'!T2+'Weekly Raw Data'!Z2+'Weekly Raw Data'!AF2+'Weekly Raw Data'!AL2+'Weekly Raw Data'!AR2+'Weekly Raw Data'!AX2+'Weekly Raw Data'!BD2+'Weekly Raw Data'!BJ2+'Weekly Raw Data'!BP2+'Weekly Raw Data'!BV2+'Weekly Raw Data'!CB2 -> 1151.9 | H3: =F3-E3 -> 100.7 | I3: =IF(E3<>0,(F3-E3)/E3,0) -> 0.095868241 | J3: =G3-E3 -> 101.5 | K3: =IF(E3<>0,(G3-E3)/E3,0) -> 0.096629855 | L3: ='Weekly Raw Data'!I2+'Weekly Raw Data'!O2+'Weekly Raw Data'!U2+'Weekly Raw Data'!AA2+'Weekly Raw Data'!AG2+'Weekly Raw Data'!AM2+'Weekly Raw Data'!AS2+'Weekly Raw Data'!AY2+'Weekly Raw Data'!BE2+'Weekly Raw Data'!BK2+'Weekly Raw Data'!BQ2+'Weekly Raw Data'!BW2+'Weekly Raw Data'!CC2 -> 188.5 | M3: ='Weekly Raw Data'!J2+'Weekly Raw Data'!P2+'Weekly Raw Data'!V2+'Weekly Raw Data'!AB2+'Weekly Raw Data'!AH2+'Weekly Raw Data'!AN2+'Weekly Raw Data'!AT2+'Weekly Raw Data'!AZ2+'Weekly Raw Data'!BF2+'Weekly Raw Data'!BL2+'Weekly Raw Data'!BR2+'Weekly Raw Data'!BX2+'Weekly Raw Data'!CD2 -> 208.5 | N3: ='Weekly Raw Data'!K2+'Weekly Raw Data'!Q2+'Weekly Raw Data'!W2+'Weekly Raw Data'!AC2+'Weekly Raw Data'!AI2+'Weekly Raw Data'!AO2+'Weekly Raw Data'!AU2+'Weekly Raw Data'!BA2+'Weekly Raw Data'!BG2+'Weekly Raw Data'!BM2+'Weekly Raw Data'!BS2+'Weekly Raw Data'!BY2+'Weekly Raw Data'!CE2 -> 203.9 | O3: =M3-L3 -> 20 | P3: =IF(L3<>0,(M3-L3)/L3,0) -> 0.1061008 | Q3: =F3-M3 -> 942.6 | R3: =E3-L3 -> 861.9 | S3: =Q3-R3 -> 80.7
A4: PF-002 | B4: NutriPaws | C4: Dry Dog Food | D4: Grocery | E4: ='Weekly Raw Data'!F3+'Weekly Raw Data'!L3+'Weekly Raw Data'!R3+'Weekly Raw Data'!X3+'Weekly Raw Data'!AD3+'Weekly Raw Data'!AJ3+'Weekly Raw Data'!AP3+'Weekly Raw Data'!AV3+'Weekly Raw Data'!BB3+'Weekly Raw Data'!BH3+'Weekly Raw Data'!BN3+'Weekly Raw Data'!BT3+'Weekly Raw Data'!BZ3 -> 1950 | F4: ='Weekly Raw Data'!G3+'Weekly Raw Data'!M3+'Weekly Raw Data'!S3+'Weekly Raw Data'!Y3+'Weekly Raw Data'!AE3+'Weekly Raw Data'!AK3+'Weekly Raw Data'!AQ3+'Weekly Raw Data'!AW3+'Weekly Raw Data'!BC3+'Weekly Raw Data'!BI3+'Weekly Raw Data'!BO3+'Weekly Raw Data'!BU3+'Weekly Raw Data'!CA3 -> 2135.1 | G4: ='Weekly Raw Data'!H3+'Weekly Raw Data'!N3+'Weekly Raw Data'!T3+'Weekly Raw Data'!Z3+'Weekly Raw Data'!AF3+'Weekly Raw Data'!AL3+'Weekly Raw Data'!AR3+'Weekly Raw Data'!AX3+'Weekly Raw Data'!BD3+'Weekly Raw Data'!BJ3+'Weekly Raw Data'!BP3+'Weekly Raw Data'!BV3+'Weekly Raw Data'!CB3 -> 2143.9 | H4: =F4-E4 -> 185.1 | I4: =IF(E4<>0,(F4-E4)/E4,0) -> 0.094923077 | J4: =G4-E4 -> 193.9 | K4: =IF(E4<>0,(G4-E4)/E4,0) -> 0.099435897 | L4: ='Weekly Raw Data'!I3+'Weekly Raw Data'!O3+'Weekly Raw Data'!U3+'Weekly Raw Data'!AA3+'Weekly Raw Data'!AG3+'Weekly Raw Data'!AM3+'Weekly Raw Data'!AS3+'Weekly Raw Data'!AY3+'Weekly Raw Data'!BE3+'Weekly Raw Data'!BK3+'Weekly Raw Data'!BQ3+'Weekly Raw Data'!BW3+'Weekly Raw Data'!CC3 -> 390 | M4: ='Weekly Raw Data'!J3+'Weekly Raw Data'!P3+'Weekly Raw Data'!V3+'Weekly Raw Data'!AB3+'Weekly Raw Data'!AH3+'Weekly Raw Data'!AN3+'Weekly Raw Data'!AT3+'Weekly Raw Data'!AZ3+'Weekly Raw Data'!BF3+'Weekly Raw Data'!BL3+'Weekly Raw Data'!BR3+'Weekly Raw Data'!BX3+'Weekly Raw Data'!CD3 -> 427.7 | N4: ='Weekly Raw Data'!K3+'Weekly Raw Data'!Q3+'Weekly Raw Data'!W3+'Weekly Raw Data'!AC3+'Weekly Raw Data'!AI3+'Weekly Raw Data'!AO3+'Weekly Raw Data'!AU3+'Weekly Raw Data'!BA3+'Weekly Raw Data'!BG3+'Weekly Raw Data'!BM3+'Weekly Raw Data'!BS3+'Weekly Raw Data'!BY3+'Weekly Raw Data'!CE3 -> 430.2 | O4: =M4-L4 -> 37.7 | P4: =IF(L4<>0,(M4-L4)/L4,0) -> 0.096666667 | Q4: =F4-M4 -> 1707.4 | R4: =E4-L4 -> 1560 | S4: =Q4-R4 -> 147.4
A5: PF-003 | B5: NutriPaws | C5: Wet Dog Food | D5: Grocery | E5: ='Weekly Raw Data'!F4+'Weekly Raw Data'!L4+'Weekly Raw Data'!R4+'Weekly Raw Data'!X4+'Weekly Raw Data'!AD4+'Weekly Raw Data'!AJ4+'Weekly Raw Data'!AP4+'Weekly Raw Data'!AV4+'Weekly Raw Data'!BB4+'Weekly Raw Data'!BH4+'Weekly Raw Data'!BN4+'Weekly Raw Data'!BT4+'Weekly Raw Data'!BZ4 -> 774.8 | F5: ='Weekly Raw Data'!G4+'Weekly Raw Data'!M4+'Weekly Raw Data'!S4+'Weekly Raw Data'!Y4+'Weekly Raw Data'!AE4+'Weekly Raw Data'!AK4+'Weekly Raw Data'!AQ4+'Weekly Raw Data'!AW4+'Weekly Raw Data'!BC4+'Weekly Raw Data'!BI4+'Weekly Raw Data'!BO4+'Weekly Raw Data'!BU4+'Weekly Raw Data'!CA4 -> 848.9 | G5: ='Weekly Raw Data'!H4+'Weekly Raw Data'!N4+'Weekly Raw Data'!T4+'Weekly Raw Data'!Z4+'Weekly Raw Data'!AF4+'Weekly Raw Data'!AL4+'Weekly Raw Data'!AR4+'Weekly Raw Data'!AX4+'Weekly Raw Data'!BD4+'Weekly Raw Data'!BJ4+'Weekly Raw Data'!BP4+'Weekly Raw Data'!BV4+'Weekly Raw Data'!CB4 -> 857.8 | H5: =F5-E5 -> 74.1 | I5: =IF(E5<>0,(F5-E5)/E5,0) -> 0.095637584 | J5: =G5-E5 -> 83 | K5: =IF(E5<>0,(G5-E5)/E5,0) -> 0.10712442 | L5: ='Weekly Raw Data'!I4+'Weekly Raw Data'!O4+'Weekly Raw Data'!U4+'Weekly Raw Data'!AA4+'Weekly Raw Data'!AG4+'Weekly Raw Data'!AM4+'Weekly Raw Data'!AS4+'Weekly Raw Data'!AY4+'Weekly Raw Data'!BE4+'Weekly Raw Data'!BK4+'Weekly Raw Data'!BQ4+'Weekly Raw Data'!BW4+'Weekly Raw Data'!CC4 -> 170.3 | M5: ='Weekly Raw Data'!J4+'Weekly Raw Data'!P4+'Weekly Raw Data'!V4+'Weekly Raw Data'!AB4+'Weekly Raw Data'!AH4+'Weekly Raw Data'!AN4+'Weekly Raw Data'!AT4+'Weekly Raw Data'!AZ4+'Weekly Raw Data'!BF4+'Weekly Raw Data'!BL4+'Weekly Raw Data'!BR4+'Weekly Raw Data'!BX4+'Weekly Raw Data'!CD4 -> 188 | N5: ='Weekly Raw Data'!K4+'Weekly Raw Data'!Q4+'Weekly Raw Data'!W4+'Weekly Raw Data'!AC4+'Weekly Raw Data'!AI4+'Weekly Raw Data'!AO4+'Weekly Raw Data'!AU4+'Weekly Raw Data'!BA4+'Weekly Raw Data'!BG4+'Weekly Raw Data'!BM4+'Weekly Raw Data'!BS4+'Weekly Raw Data'!BY4+'Weekly Raw Data'!CE4 -> 188.3 | O5: =M5-L5 -> 17.7 | P5: =IF(L5<>0,(M5-L5)/L5,0) -> 0.10393423 | Q5: =F5-M5 -> 660.9 | R5: =E5-L5 -> 604.5 | S5: =Q5-R5 -> 56.4
A6: PF-004 | B6: VitaCat | C6: Dry Cat Food | D6: Grocery | E6: ='Weekly Raw Data'!F5+'Weekly Raw Data'!L5+'Weekly Raw Data'!R5+'Weekly Raw Data'!X5+'Weekly Raw Data'!AD5+'Weekly Raw Data'!AJ5+'Weekly Raw Data'!AP5+'Weekly Raw Data'!AV5+'Weekly Raw Data'!BB5+'Weekly Raw Data'!BH5+'Weekly Raw Data'!BN5+'Weekly Raw Data'!BT5+'Weekly Raw Data'!BZ5 -> 650 | F6: ='Weekly Raw Data'!G5+'Weekly Raw Data'!M5+'Weekly Raw Data'!S5+'Weekly Raw Data'!Y5+'Weekly Raw Data'!AE5+'Weekly Raw Data'!AK5+'Weekly Raw Data'!AQ5+'Weekly Raw Data'!AW5+'Weekly Raw Data'!BC5+'Weekly Raw Data'!BI5+'Weekly Raw Data'!BO5+'Weekly Raw Data'!BU5+'Weekly Raw Data'!CA5 -> 677 | G6: ='Weekly Raw Data'!H5+'Weekly Raw Data'!N5+'Weekly Raw Data'!T5+'Weekly Raw Data'!Z5+'Weekly Raw Data'!AF5+'Weekly Raw Data'!AL5+'Weekly Raw Data'!AR5+'Weekly Raw Data'!AX5+'Weekly Raw Data'!BD5+'Weekly Raw Data'!BJ5+'Weekly Raw Data'!BP5+'Weekly Raw Data'!BV5+'Weekly Raw Data'!CB5 -> 678.9 | H6: =F6-E6 -> 27 | I6: =IF(E6<>0,(F6-E6)/E6,0) -> 0.041538462 | J6: =G6-E6 -> 28.9 | K6: =IF(E6<>0,(G6-E6)/E6,0) -> 0.044461538 | L6: ='Weekly Raw Data'!I5+'Weekly Raw Data'!O5+'Weekly Raw Data'!U5+'Weekly Raw Data'!AA5+'Weekly Raw Data'!AG5+'Weekly Raw Data'!AM5+'Weekly Raw Data'!AS5+'Weekly Raw Data'!AY5+'Weekly Raw Data'!BE5+'Weekly Raw Data'!BK5+'Weekly Raw Data'!BQ5+'Weekly Raw Data'!BW5+'Weekly Raw Data'!CC5 -> 110.5 | M6: ='Weekly Raw Data'!J5+'Weekly Raw Data'!P5+'Weekly Raw Data'!V5+'Weekly Raw Data'!AB5+'Weekly Raw Data'!AH5+'Weekly Raw Data'!AN5+'Weekly Raw Data'!AT5+'Weekly Raw Data'!AZ5+'Weekly Raw Data'!BF5+'Weekly Raw Data'!BL5+'Weekly Raw Data'!BR5+'Weekly Raw Data'!BX5+'Weekly Raw Data'!CD5 -> 119.2 | N6: ='Weekly Raw Data'!K5+'Weekly Raw Data'!Q5+'Weekly Raw Data'!W5+'Weekly Raw Data'!AC5+'Weekly Raw Data'!AI5+'Weekly Raw Data'!AO5+'Weekly Raw Data'!AU5+'Weekly Raw Data'!BA5+'Weekly Raw Data'!BG5+'Weekly Raw Data'!BM5+'Weekly Raw Data'!BS5+'Weekly Raw Data'!BY5+'Weekly Raw Data'!CE5 -> 114.5 | O6: =M6-L6 -> 8.7 | P6: =IF(L6<>0,(M6-L6)/L6,0) -> 0.078733032 | Q6: =F6-M6 -> 557.8 | R6: =E6-L6 -> 539.5 | S6: =Q6-R6 -> 18.3
A7: PF-005 | B7: VitaCat | C7: Wet Cat Food | D7: Grocery | E7: ='Weekly Raw Data'!F6+'Weekly Raw Data'!L6+'Weekly Raw Data'!R6+'Weekly Raw Data'!X6+'Weekly Raw Data'!AD6+'Weekly Raw Data'!AJ6+'Weekly Raw Data'!AP6+'Weekly Raw Data'!AV6+'Weekly Raw Data'!BB6+'Weekly Raw Data'!BH6+'Weekly Raw Data'!BN6+'Weekly Raw Data'!BT6+'Weekly Raw Data'!BZ6 -> 474.5 | F7: ='Weekly Raw Data'!G6+'Weekly Raw Data'!M6+'Weekly Raw Data'!S6+'Weekly Raw Data'!Y6+'Weekly Raw Data'!AE6+'Weekly Raw Data'!AK6+'Weekly Raw Data'!AQ6+'Weekly Raw Data'!AW6+'Weekly Raw Data'!BC6+'Weekly Raw Data'!BI6+'Weekly Raw Data'!BO6+'Weekly Raw Data'!BU6+'Weekly Raw Data'!CA6 -> 506 | G7: ='Weekly Raw Data'!H6+'Weekly Raw Data'!N6+'Weekly Raw Data'!T6+'Weekly Raw Data'!Z6+'Weekly Raw Data'!AF6+'Weekly Raw Data'!AL6+'Weekly Raw Data'!AR6+'Weekly Raw Data'!AX6+'Weekly Raw Data'!BD6+'Weekly Raw Data'!BJ6+'Weekly Raw Data'!BP6+'Weekly Raw Data'!BV6+'Weekly Raw Data'!CB6 -> 511.3 | H7: =F7-E7 -> 31.5 | I7: =IF(E7<>0,(F7-E7)/E7,0) -> 0.066385669 | J7: =G7-E7 -> 36.8 | K7: =IF(E7<>0,(G7-E7)/E7,0) -> 0.077555321 | L7: ='Weekly Raw Data'!I6+'Weekly Raw Data'!O6+'Weekly Raw Data'!U6+'Weekly Raw Data'!AA6+'Weekly Raw Data'!AG6+'Weekly Raw Data'!AM6+'Weekly Raw Data'!AS6+'Weekly Raw Data'!AY6+'Weekly Raw Data'!BE6+'Weekly Raw Data'!BK6+'Weekly Raw Data'!BQ6+'Weekly Raw Data'!BW6+'Weekly Raw Data'!CC6 -> 118.3 | M7: ='Weekly Raw Data'!J6+'Weekly Raw Data'!P6+'Weekly Raw Data'!V6+'Weekly Raw Data'!AB6+'Weekly Raw Data'!AH6+'Weekly Raw Data'!AN6+'Weekly Raw Data'!AT6+'Weekly Raw Data'!AZ6+'Weekly Raw Data'!BF6+'Weekly Raw Data'!BL6+'Weekly Raw Data'!BR6+'Weekly Raw Data'!BX6+'Weekly Raw Data'!CD6 -> 126 | N7: ='Weekly Raw Data'!K6+'Weekly Raw Data'!Q6+'Weekly Raw Data'!W6+'Weekly Raw Data'!AC6+'Weekly Raw Data'!AI6+'Weekly Raw Data'!AO6+'Weekly Raw Data'!AU6+'Weekly Raw Data'!BA6+'Weekly Raw Data'!BG6+'Weekly Raw Data'!BM6+'Weekly Raw Data'!BS6+'Weekly Raw Data'!BY6+'Weekly Raw Data'!CE6 -> 129.8 | O7: =M7-L7 -> 7.7 | P7: =IF(L7<>0,(M7-L7)/L7,0) -> 0.065088757 | Q7: =F7-M7 -> 380 | R7: =E7-L7 -> 356.2 | S7: =Q7-R7 -> 23.8
A8: PF-006 | B8: VitaCat | C8: Dry Cat Food | D8: Mass | E8: ='Weekly Raw Data'!F7+'Weekly Raw Data'!L7+'Weekly Raw Data'!R7+'Weekly Raw Data'!X7+'Weekly Raw Data'!AD7+'Weekly Raw Data'!AJ7+'Weekly Raw Data'!AP7+'Weekly Raw Data'!AV7+'Weekly Raw Data'!BB7+'Weekly Raw Data'!BH7+'Weekly Raw Data'!BN7+'Weekly Raw Data'!BT7+'Weekly Raw Data'!BZ7 -> 850.2 | F8: ='Weekly Raw Data'!G7+'Weekly Raw Data'!M7+'Weekly Raw Data'!S7+'Weekly Raw Data'!Y7+'Weekly Raw Data'!AE7+'Weekly Raw Data'!AK7+'Weekly Raw Data'!AQ7+'Weekly Raw Data'!AW7+'Weekly Raw Data'!BC7+'Weekly Raw Data'!BI7+'Weekly Raw Data'!BO7+'Weekly Raw Data'!BU7+'Weekly Raw Data'!CA7 -> 910.3 | G8: ='Weekly Raw Data'!H7+'Weekly Raw Data'!N7+'Weekly Raw Data'!T7+'Weekly Raw Data'!Z7+'Weekly Raw Data'!AF7+'Weekly Raw Data'!AL7+'Weekly Raw Data'!AR7+'Weekly Raw Data'!AX7+'Weekly Raw Data'!BD7+'Weekly Raw Data'!BJ7+'Weekly Raw Data'!BP7+'Weekly Raw Data'!BV7+'Weekly Raw Data'!CB7 -> 913.3 | H8: =F8-E8 -> 60.1 | I8: =IF(E8<>0,(F8-E8)/E8,0) -> 0.07068925 | J8: =G8-E8 -> 63.1 | K8: =IF(E8<>0,(G8-E8)/E8,0) -> 0.074217831 | L8: ='Weekly Raw Data'!I7+'Weekly Raw Data'!O7+'Weekly Raw Data'!U7+'Weekly Raw Data'!AA7+'Weekly Raw Data'!AG7+'Weekly Raw Data'!AM7+'Weekly Raw Data'!AS7+'Weekly Raw Data'!AY7+'Weekly Raw Data'!BE7+'Weekly Raw Data'!BK7+'Weekly Raw Data'!BQ7+'Weekly Raw Data'!BW7+'Weekly Raw Data'!CC7 -> 161.2 | M8: ='Weekly Raw Data'!J7+'Weekly Raw Data'!P7+'Weekly Raw Data'!V7+'Weekly Raw Data'!AB7+'Weekly Raw Data'!AH7+'Weekly Raw Data'!AN7+'Weekly Raw Data'!AT7+'Weekly Raw Data'!AZ7+'Weekly Raw Data'!BF7+'Weekly Raw Data'!BL7+'Weekly Raw Data'!BR7+'Weekly Raw Data'!BX7+'Weekly Raw Data'!CD7 -> 175.7 | N8: ='Weekly Raw Data'!K7+'Weekly Raw Data'!Q7+'Weekly Raw Data'!W7+'Weekly Raw Data'!AC7+'Weekly Raw Data'!AI7+'Weekly Raw Data'!AO7+'Weekly Raw Data'!AU7+'Weekly Raw Data'!BA7+'Weekly Raw Data'!BG7+'Weekly Raw Data'!BM7+'Weekly Raw Data'!BS7+'Weekly Raw Data'!BY7+'Weekly Raw Data'!CE7 -> 173.3 | O8: =M8-L8 -> 14.5 | P8: =IF(L8<>0,(M8-L8)/L8,0) -> 0.089950372 | Q8: =F8-M8 -> 734.6 | R8: =E8-L8 -> 689 | S8: =Q8-R8 -> 45.6
A9: PF-007 | B9: PureProtein | C9: Dry Dog Food | D9: Mass | E9: ='Weekly Raw Data'!F8+'Weekly Raw Data'!L8+'Weekly Raw Data'!R8+'Weekly Raw Data'!X8+'Weekly Raw Data'!AD8+'Weekly Raw Data'!AJ8+'Weekly Raw Data'!AP8+'Weekly Raw Data'!AV8+'Weekly Raw Data'!BB8+'Weekly Raw Data'!BH8+'Weekly Raw Data'!BN8+'Weekly Raw Data'!BT8+'Weekly Raw Data'!BZ8 -> 1275.3 | F9: ='Weekly Raw Data'!G8+'Weekly Raw Data'!M8+'Weekly Raw Data'!S8+'Weekly Raw Data'!Y8+'Weekly Raw Data'!AE8+'Weekly Raw Data'!AK8+'Weekly Raw Data'!AQ8+'Weekly Raw Data'!AW8+'Weekly Raw Data'!BC8+'Weekly Raw Data'!BI8+'Weekly Raw Data'!BO8+'Weekly Raw Data'!BU8+'Weekly Raw Data'!CA8 -> 1395.9 | G9: ='Weekly Raw Data'!H8+'Weekly Raw Data'!N8+'Weekly Raw Data'!T8+'Weekly Raw Data'!Z8+'Weekly Raw Data'!AF8+'Weekly Raw Data'!AL8+'Weekly Raw Data'!AR8+'Weekly Raw Data'!AX8+'Weekly Raw Data'!BD8+'Weekly Raw Data'!BJ8+'Weekly Raw Data'!BP8+'Weekly Raw Data'!BV8+'Weekly Raw Data'!CB8 -> 1401.2 | H9: =F9-E9 -> 120.6 | I9: =IF(E9<>0,(F9-E9)/E9,0) -> 0.094565984 | J9: =G9-E9 -> 125.9 | K9: =IF(E9<>0,(G9-E9)/E9,0) -> 0.098721869 | L9: ='Weekly Raw Data'!I8+'Weekly Raw Data'!O8+'Weekly Raw Data'!U8+'Weekly Raw Data'!AA8+'Weekly Raw Data'!AG8+'Weekly Raw Data'!AM8+'Weekly Raw Data'!AS8+'Weekly Raw Data'!AY8+'Weekly Raw Data'!BE8+'Weekly Raw Data'!BK8+'Weekly Raw Data'!BQ8+'Weekly Raw Data'!BW8+'Weekly Raw Data'!CC8 -> 267.8 | M9: ='Weekly Raw Data'!J8+'Weekly Raw Data'!P8+'Weekly Raw Data'!V8+'Weekly Raw Data'!AB8+'Weekly Raw Data'!AH8+'Weekly Raw Data'!AN8+'Weekly Raw Data'!AT8+'Weekly Raw Data'!AZ8+'Weekly Raw Data'!BF8+'Weekly Raw Data'!BL8+'Weekly Raw Data'!BR8+'Weekly Raw Data'!BX8+'Weekly Raw Data'!CD8 -> 303 | N9: ='Weekly Raw Data'!K8+'Weekly Raw Data'!Q8+'Weekly Raw Data'!W8+'Weekly Raw Data'!AC8+'Weekly Raw Data'!AI8+'Weekly Raw Data'!AO8+'Weekly Raw Data'!AU8+'Weekly Raw Data'!BA8+'Weekly Raw Data'!BG8+'Weekly Raw Data'!BM8+'Weekly Raw Data'!BS8+'Weekly Raw Data'!BY8+'Weekly Raw Data'!CE8 -> 295.6 | O9: =M9-L9 -> 35.2 | P9: =IF(L9<>0,(M9-L9)/L9,0) -> 0.13144137 | Q9: =F9-M9 -> 1092.9 | R9: =E9-L9 -> 1007.5 | S9: =Q9-R9 -> 85.4
A10: PF-008 | B10: PureProtein | C10: Treats & Snacks | D10: Grocery | E10: ='Weekly Raw Data'!F9+'Weekly Raw Data'!L9+'Weekly Raw Data'!R9+'Weekly Raw Data'!X9+'Weekly Raw Data'!AD9+'Weekly Raw Data'!AJ9+'Weekly Raw Data'!AP9+'Weekly Raw Data'!AV9+'Weekly Raw Data'!BB9+'Weekly Raw Data'!BH9+'Weekly Raw Data'!BN9+'Weekly Raw Data'!BT9+'Weekly Raw Data'!BZ9 -> 300.3 | F10: ='Weekly Raw Data'!G9+'Weekly Raw Data'!M9+'Weekly Raw Data'!S9+'Weekly Raw Data'!Y9+'Weekly Raw Data'!AE9+'Weekly Raw Data'!AK9+'Weekly Raw Data'!AQ9+'Weekly Raw Data'!AW9+'Weekly Raw Data'!BC9+'Weekly Raw Data'!BI9+'Weekly Raw Data'!BO9+'Weekly Raw Data'!BU9+'Weekly Raw Data'!CA9 -> 318.7 | G10: ='Weekly Raw Data'!H9+'Weekly Raw Data'!N9+'Weekly Raw Data'!T9+'Weekly Raw Data'!Z9+'Weekly Raw Data'!AF9+'Weekly Raw Data'!AL9+'Weekly Raw Data'!AR9+'Weekly Raw Data'!AX9+'Weekly Raw Data'!BD9+'Weekly Raw Data'!BJ9+'Weekly Raw Data'!BP9+'Weekly Raw Data'!BV9+'Weekly Raw Data'!CB9 -> 319 | H10: =F10-E10 -> 18.4 | I10: =IF(E10<>0,(F10-E10)/E10,0) -> 0.061272061 | J10: =G10-E10 -> 18.7 | K10: =IF(E10<>0,(G10-E10)/E10,0) -> 0.062271062 | L10: ='Weekly Raw Data'!I9+'Weekly Raw Data'!O9+'Weekly Raw Data'!U9+'Weekly Raw Data'!AA9+'Weekly Raw Data'!AG9+'Weekly Raw Data'!AM9+'Weekly Raw Data'!AS9+'Weekly Raw Data'!AY9+'Weekly Raw Data'!BE9+'Weekly Raw Data'!BK9+'Weekly Raw Data'!BQ9+'Weekly Raw Data'!BW9+'Weekly Raw Data'!CC9 -> 45.5 | M10: ='Weekly Raw Data'!J9+'Weekly Raw Data'!P9+'Weekly Raw Data'!V9+'Weekly Raw Data'!AB9+'Weekly Raw Data'!AH9+'Weekly Raw Data'!AN9+'Weekly Raw Data'!AT9+'Weekly Raw Data'!AZ9+'Weekly Raw Data'!BF9+'Weekly Raw Data'!BL9+'Weekly Raw Data'!BR9+'Weekly Raw Data'!BX9+'Weekly Raw Data'!CD9 -> 47.1 | N10: ='Weekly Raw Data'!K9+'Weekly Raw Data'!Q9+'Weekly Raw Data'!W9+'Weekly Raw Data'!AC9+'Weekly Raw Data'!AI9+'Weekly Raw Data'!AO9+'Weekly Raw Data'!AU9+'Weekly Raw Data'!BA9+'Weekly Raw Data'!BG9+'Weekly Raw Data'!BM9+'Weekly Raw Data'!BS9+'Weekly Raw Data'!BY9+'Weekly Raw Data'!CE9 -> 47.7 | O10: =M10-L10 -> 1.6 | P10: =IF(L10<>0,(M10-L10)/L10,0) -> 0.035164835 | Q10: =F10-M10 -> 271.6 | R10: =E10-L10 -> 254.8 | S10: =Q10-R10 -> 16.8
A11: PF-009 | B11: PureProtein | C11: Treats & Snacks | D11: Mass | E11: ='Weekly Raw Data'!F10+'Weekly Raw Data'!L10+'Weekly Raw Data'!R10+'Weekly Raw Data'!X10+'Weekly Raw Data'!AD10+'Weekly Raw Data'!AJ10+'Weekly Raw Data'!AP10+'Weekly Raw Data'!AV10+'Weekly Raw Data'!BB10+'Weekly Raw Data'!BH10+'Weekly Raw Data'!BN10+'Weekly Raw Data'!BT10+'Weekly Raw Data'!BZ10 -> 449.8 | F11: ='Weekly Raw Data'!G10+'Weekly Raw Data'!M10+'Weekly Raw Data'!S10+'Weekly Raw Data'!Y10+'Weekly Raw Data'!AE10+'Weekly Raw Data'!AK10+'Weekly Raw Data'!AQ10+'Weekly Raw Data'!AW10+'Weekly Raw Data'!BC10+'Weekly Raw Data'!BI10+'Weekly Raw Data'!BO10+'Weekly Raw Data'!BU10+'Weekly Raw Data'!CA10 -> 487.1 | G11: ='Weekly Raw Data'!H10+'Weekly Raw Data'!N10+'Weekly Raw Data'!T10+'Weekly Raw Data'!Z10+'Weekly Raw Data'!AF10+'Weekly Raw Data'!AL10+'Weekly Raw Data'!AR10+'Weekly Raw Data'!AX10+'Weekly Raw Data'!BD10+'Weekly Raw Data'!BJ10+'Weekly Raw Data'!BP10+'Weekly Raw Data'!BV10+'Weekly Raw Data'!CB10 -> 491.7 | H11: =F11-E11 -> 37.3 | I11: =IF(E11<>0,(F11-E11)/E11,0) -> 0.082925745 | J11: =G11-E11 -> 41.9 | K11: =IF(E11<>0,(G11-E11)/E11,0) -> 0.093152512 | L11: ='Weekly Raw Data'!I10+'Weekly Raw Data'!O10+'Weekly Raw Data'!U10+'Weekly Raw Data'!AA10+'Weekly Raw Data'!AG10+'Weekly Raw Data'!AM10+'Weekly Raw Data'!AS10+'Weekly Raw Data'!AY10+'Weekly Raw Data'!BE10+'Weekly Raw Data'!BK10+'Weekly Raw Data'!BQ10+'Weekly Raw Data'!BW10+'Weekly Raw Data'!CC10 -> 71.5 | M11: ='Weekly Raw Data'!J10+'Weekly Raw Data'!P10+'Weekly Raw Data'!V10+'Weekly Raw Data'!AB10+'Weekly Raw Data'!AH10+'Weekly Raw Data'!AN10+'Weekly Raw Data'!AT10+'Weekly Raw Data'!AZ10+'Weekly Raw Data'!BF10+'Weekly Raw Data'!BL10+'Weekly Raw Data'!BR10+'Weekly Raw Data'!BX10+'Weekly Raw Data'!CD10 -> 78.5 | N11: ='Weekly Raw Data'!K10+'Weekly Raw Data'!Q10+'Weekly Raw Data'!W10+'Weekly Raw Data'!AC10+'Weekly Raw Data'!AI10+'Weekly Raw Data'!AO10+'Weekly Raw Data'!AU10+'Weekly Raw Data'!BA10+'Weekly Raw Data'!BG10+'Weekly Raw Data'!BM10+'Weekly Raw Data'!BS10+'Weekly Raw Data'!BY10+'Weekly Raw Data'!CE10 -> 78.5 | O11: =M11-L11 -> 7 | P11: =IF(L11<>0,(M11-L11)/L11,0) -> 0.097902098 | Q11: =F11-M11 -> 408.6 | R11: =E11-L11 -> 378.3 | S11: =Q11-R11 -> 30.3
A12: PF-010 | B12: NutriPaws | C12: Dry Dog Food | D12: Pet Specialty | E12: ='Weekly Raw Data'!F11+'Weekly Raw Data'!L11+'Weekly Raw Data'!R11+'Weekly Raw Data'!X11+'Weekly Raw Data'!AD11+'Weekly Raw Data'!AJ11+'Weekly Raw Data'!AP11+'Weekly Raw Data'!AV11+'Weekly Raw Data'!BB11+'Weekly Raw Data'!BH11+'Weekly Raw Data'!BN11+'Weekly Raw Data'!BT11+'Weekly Raw Data'!BZ11 -> 1625 | F12: ='Weekly Raw Data'!G11+'Weekly Raw Data'!M11+'Weekly Raw Data'!S11+'Weekly Raw Data'!Y11+'Weekly Raw Data'!AE11+'Weekly Raw Data'!AK11+'Weekly Raw Data'!AQ11+'Weekly Raw Data'!AW11+'Weekly Raw Data'!BC11+'Weekly Raw Data'!BI11+'Weekly Raw Data'!BO11+'Weekly Raw Data'!BU11+'Weekly Raw Data'!CA11 -> 1743.4 | G12: ='Weekly Raw Data'!H11+'Weekly Raw Data'!N11+'Weekly Raw Data'!T11+'Weekly Raw Data'!Z11+'Weekly Raw Data'!AF11+'Weekly Raw Data'!AL11+'Weekly Raw Data'!AR11+'Weekly Raw Data'!AX11+'Weekly Raw Data'!BD11+'Weekly Raw Data'!BJ11+'Weekly Raw Data'!BP11+'Weekly Raw Data'!BV11+'Weekly Raw Data'!CB11 -> 1732.4 | H12: =F12-E12 -> 118.4 | I12: =IF(E12<>0,(F12-E12)/E12,0) -> 0.072861538 | J12: =G12-E12 -> 107.4 | K12: =IF(E12<>0,(G12-E12)/E12,0) -> 0.066092308 | L12: ='Weekly Raw Data'!I11+'Weekly Raw Data'!O11+'Weekly Raw Data'!U11+'Weekly Raw Data'!AA11+'Weekly Raw Data'!AG11+'Weekly Raw Data'!AM11+'Weekly Raw Data'!AS11+'Weekly Raw Data'!AY11+'Weekly Raw Data'!BE11+'Weekly Raw Data'!BK11+'Weekly Raw Data'!BQ11+'Weekly Raw Data'!BW11+'Weekly Raw Data'!CC11 -> 374.4 | M12: ='Weekly Raw Data'!J11+'Weekly Raw Data'!P11+'Weekly Raw Data'!V11+'Weekly Raw Data'!AB11+'Weekly Raw Data'!AH11+'Weekly Raw Data'!AN11+'Weekly Raw Data'!AT11+'Weekly Raw Data'!AZ11+'Weekly Raw Data'!BF11+'Weekly Raw Data'!BL11+'Weekly Raw Data'!BR11+'Weekly Raw Data'!BX11+'Weekly Raw Data'!CD11 -> 394.5 | N12: ='Weekly Raw Data'!K11+'Weekly Raw Data'!Q11+'Weekly Raw Data'!W11+'Weekly Raw Data'!AC11+'Weekly Raw Data'!AI11+'Weekly Raw Data'!AO11+'Weekly Raw Data'!AU11+'Weekly Raw Data'!BA11+'Weekly Raw Data'!BG11+'Weekly Raw Data'!BM11+'Weekly Raw Data'!BS11+'Weekly Raw Data'!BY11+'Weekly Raw Data'!CE11 -> 401.4 | O12: =M12-L12 -> 20.1 | P12: =IF(L12<>0,(M12-L12)/L12,0) -> 0.053685897 | Q12: =F12-M12 -> 1348.9 | R12: =E12-L12 -> 1250.6 | S12: =Q12-R12 -> 98.3
A13: TOTAL | E13: =SUM(E3:E12) -> 9400.3 | F13: =SUM(F3:F12) -> 10173.5 | G13: =SUM(G3:G12) -> 10201.4 | H13: =SUM(H3:H12) -> 773.2 | I13: =IF(SUM(E3:E12)<>0,(SUM(F3:F12)-SUM(E3:E12))/SUM(E3:E12),0) -> 0.082252694 | J13: =SUM(J3:J12) -> 801.1 | K13: =IF(SUM(G3:G12)<>0,(SUM(G3:G12)-SUM(G3:G12))/SUM(G3:G12),0) -> 0 | L13: =SUM(L3:L12) -> 1898 | M13: =SUM(M3:M12) -> 2068.2 | N13: =SUM(N3:N12) -> 2063.2 | O13: =SUM(O3:O12) -> 170.2 | P13: =IF(SUM(L3:L12)<>0,(SUM(M3:M12)-SUM(L3:L12))/SUM(L3:L12),0) -> 0.08967334 | Q13: =SUM(Q3:Q12) -> 8105.3 | R13: =SUM(R3:R12) -> 7502.3 | S13: =SUM(S3:S12) -> 603

Sheet Weekly GSV Trend
A1: Weekly GSV: LE vs Plan by SKU – Last 13 Weeks ($K)
A2: SKU / Brand | B2: W1 (29-Dec) | C2: W2 (05-Jan) | D2: W3 (12-Jan) | E2: W4 (19-Jan) | F2: W5 (26-Jan) | G2: W6 (02-Feb) | H2: W7 (09-Feb) | I2: W8 (16-Feb) | J2: W9 (23-Feb) | K2: W10 (02-Mar) | L2: W11 (09-Mar) | M2: W12 (16-Mar) | N2: W13 (23-Mar)
A3: PF-001 – NutriPaws | B3: 84.5 | C3: 114.6 | D3: 84.2 | E3: 81.2 | F3: 80.3 | G3: 113.3 | H3: 74.4 | I3: 81.6 | J3: 80.2 | K3: 114.4 | L3: 79 | M3: 77.8 | N3: 77.6
A4: PF-002 – NutriPaws | B4: 154.3 | C4: 158.9 | D4: 192.8 | E4: 160.8 | F4: 151.6 | G4: 151.6 | H4: 202.8 | I4: 164.3 | J4: 149.1 | K4: 141.9 | L4: 191.5 | M4: 144.6 | N4: 153.6
A5: PF-003 – NutriPaws | B5: 80.4 | C5: 54.2 | D5: 60.6 | E5: 58.5 | F5: 78.8 | G5: 59.6 | H5: 54.4 | I5: 56.9 | J5: 76 | K5: 64.5 | L5: 53.6 | M5: 60.9 | N5: 73.3
A6: PF-004 – VitaCat | B6: 52.3 | C6: 52.1 | D6: 48.8 | E6: 64.3 | F6: 52.9 | G6: 51.8 | H6: 52 | I6: 70.7 | J6: 51.3 | K6: 52.6 | L6: 46.5 | M6: 46.7 | N6: 47.8
A7: PF-005 – VitaCat | B7: 39.1 | C7: 51.1 | D7: 38.9 | E7: 33.6 | F7: 36.3 | G7: 47.3 | H7: 34.4 | I7: 36 | J7: 33.2 | K7: 51.9 | L7: 36 | M7: 40 | N7: 38.8
A8: PF-006 – VitaCat | B8: 69.9 | C8: 67.8 | D8: 85.9 | E8: 70.4 | F8: 62.8 | G8: 71.1 | H8: 66.8 | I8: 70.6 | J8: 64.6 | K8: 64.1 | L8: 88 | M8: 68.6 | N8: 64.3
A9: PF-007 – PureProtein | B9: 146.2 | C9: 95.6 | D9: 94.5 | E9: 101.1 | F9: 100.6 | G9: 93 | H9: 131.8 | I9: 107.8 | J9: 91.5 | K9: 94.2 | L9: 90.4 | M9: 102.3 | N9: 124.8
A10: PF-008 – PureProtein | B10: 22.4 | C10: 21.4 | D10: 23.1 | E10: 23.1 | F10: 31.5 | G10: 22.8 | H10: 21.6 | I10: 24.2 | J10: 29.5 | K10: 22.4 | L10: 24.2 | M10: 22.7 | N10: 22.2
A11: PF-009 – PureProtein | B11: 34.5 | C11: 34.6 | D11: 32.4 | E11: 49.6 | F11: 35.8 | G11: 35 | H11: 34.6 | I11: 45.9 | J11: 32.9 | K11: 37 | L11: 32.8 | M11: 49.9 | N11: 35.2
A12: PF-010 – NutriPaws | B12: 121.9 | C12: 179.9 | D12: 127.4 | E12: 117.4 | F12: 123.8 | G12: 173.9 | H12: 122.1 | I12: 133.2 | J12: 130.9 | K12: 175.4 | L12: 135.5 | M12: 115.5 | N12: 116.5
A14: Green = LE ≥ Plan | Red = LE < Plan

Sheet Data Dictionary
A1: Data Dictionary – Pet Food RGM Synthetic Dataset
A2: Field | B2: Definition | C2: Source / Notes
A3: GSV (Gross Sales Value) | B3: Revenue before trade deductions, at invoiced price ($K) | C3: Internal ERP / SAP
A4: NSV (Net Sales Value) | B4: GSV minus all trade spend deductions ($K) | C4: Calculated: GSV – Trade
A5: Trade Spend (TPM) | B5: Promotion & customer investment tracked in Trade Promo Mgmt system ($K) | C5: TPM System
A6: Trade Spend (Non-TPM) | B6: Off-system trade commitments (e.g., co-op, EDLPs) ($K) | C6: Finance Accruals
A7: Plan | B7: Locked annual operating plan, prorated to weekly ($K) | C7: Annual Planning Cycle
A8: LE (Latest Estimate) | B8: Most current forward projection of year-end landing, refreshed periodically | C8: Monthly S&OP / Finance
A9: Actual | B9: Confirmed shipped/invoiced revenue or spend for the period ($K) | C9: ERP Actuals
A10: Variance (Actual vs Plan) | B10: Actual minus Plan; positive = favourable for GSV, unfavourable for Trade | C10: Calculated
A11: Variance (LE vs Plan) | B11: LE minus Plan; forward-looking gap signal | C11: Calculated
A12: Promo Week | B12: Week flagged for trade promotion event (drives GSV uplift ~35%) | C12: Synthetic assumption
